simple_image_gallery/__init__.py
simple_image_gallery/__main__.py
simple_image_gallery/configuration/__init__.py
simple_image_gallery/configuration/config.py
simple_image_gallery/configuration/modules.py
simple_image_gallery/controller/__init__.py
simple_image_gallery/controller/images.py
simple_image_gallery/controller/index.py
simple_image_gallery/controller/slideshow.py
simple_image_gallery/services/__init__.py
simple_image_gallery/services/base.py
simple_image_gallery/services/images.py
simple_image_gallery/static/bootstrap/css/bootstrap.min.css
simple_image_gallery/static/bootstrap/js/bootstrap.min.js
simple_image_gallery/static/css/styles.min.css
simple_image_gallery/static/fonts/Inter-1b621eda4be3428e50a0ee070c09005b.woff2
simple_image_gallery/static/fonts/Inter-501638185f142ea970e06ff6a896cf44.woff2
simple_image_gallery/static/fonts/Inter-69c9fb2f299f5f5be8d2800cd24271f9.woff2
simple_image_gallery/static/fonts/Inter-6b97bb4aa11fb6d8c29b378b87c8ce45.woff2
simple_image_gallery/static/fonts/Inter-8b0bd5934b903f2631853751aedf28a6.woff2
simple_image_gallery/static/fonts/Inter-8d07e5f373f5bb3603b3e139f63e3386.woff2
simple_image_gallery/static/fonts/Inter-8e1d10adf40d7223fbee98b930853a8a.woff2
simple_image_gallery/static/fonts/Inter-991ff15c49155ffbda53e3aa14ecb8b6.woff2
simple_image_gallery/static/fonts/Inter-9f11e6095a39b5e188d6a081f05299fb.woff2
simple_image_gallery/static/fonts/Inter-aa0964911973a0fbaf081bae32a490f3.woff2
simple_image_gallery/static/fonts/Inter-c0b8741a9d891c8088e6db8ca3a4b5fa.woff2
simple_image_gallery/static/fonts/Inter-d48b1d4d308900f0591fb3bdcf442fdf.woff2
simple_image_gallery/static/fonts/Inter-d845be6713e4acd3766e1f8f6418c97e.woff2
simple_image_gallery/static/fonts/Inter-db78de5246196d0d93187248cbebc6c2.woff2
simple_image_gallery/static/img/default.png
simple_image_gallery/static/js/script.min.js
simple_image_gallery/templates/base.html
simple_image_gallery/templates/index.html
simple_image_gallery/templates/navbar_w_items.html
simple_image_gallery-1.5.0.dist-info/licenses/LICENSE
simple_image_gallery-1.5.0.dist-info/METADATA
simple_image_gallery-1.5.0.dist-info/WHEEL
simple_image_gallery-1.5.0.dist-info/entry_points.txt
simple_image_gallery-1.5.0.dist-info/top_level.txt
simple_image_gallery-1.5.0.dist-info/RECORD
