Metadata-Version: 2.4
Name: simple-image-gallery
Version: 1.5.0
Summary: A simple image gallery web application built with Flask.
Author-email: Louke <git@jannsen.org>
License-Expression: Apache-2.0
Project-URL: Homepage, https://github.com/Louuke/simple-image-gallery
Project-URL: Repository, https://github.com/Louuke/simple-image-gallery.git
Classifier: Programming Language :: Python :: 3
Classifier: Operating System :: OS Independent
Classifier: Programming Language :: Python :: Implementation :: CPython
License-File: LICENSE
Requires-Dist: flask>=3.1.0
Requires-Dist: flask-injector>=0.15.0
Requires-Dist: pydantic-settings>=2.8.1
Requires-Dist: pydantic-extra-types>=2.10.5
Requires-Dist: waitress>=3.0.2
Provides-Extra: test
Requires-Dist: pytest>=8.3.5; extra == "test"
Dynamic: license-file
